[{"is_off": ["WASHING MACHINE", "1"]}, {"inside": [["LAUNDRY DETERGENT", "1"], ["WASHING MACHINE", "1"]]}, {"inside": [["WATER", "1"], ["WASHING MACHINE", "1"]]}, {"inside": [["CLOTHES_DRESS", "4"], ["WASHING MACHINE", "1"]]}, {"inside": [["CLOTHES_DRESS", "1"], ["WASHING MACHINE", "1"]]}, {"inside": [["CLOTHES_DRESS", "2"], ["WASHING MACHINE", "1"]]}, {"location": [["WASHING MACHINE", "1"], ["LIVING ROOM", "1"]]}, {"location": [["BASKET FOR CLOTHES", "1"], ["LIVING ROOM", "1"]]}, {"closed": ["WASHING MACHINE", "1"]}, {"atreach": [["WATER", "1"], ["WATER", "1"]]}, {"atreach": [["CLOTHES_DRESS", "1"], ["BASKET FOR CLOTHES", "1"]]}, {"atreach": [["WASHING MACHINE", "1"], ["BASKET FOR CLOTHES", "1"]]}, {"atreach": [["CLOTHES_DRESS", "2"], ["BASKET FOR CLOTHES", "1"]]}, {"atreach": [["LAUNDRY DETERGENT", "1"], ["BASKET FOR CLOTHES", "1"]]}, {"atreach": [["CLOTHES_DRESS", "4"], ["BASKET FOR CLOTHES", "1"]]}, {"atreach": [["BASKET FOR CLOTHES", "1"], ["BASKET FOR CLOTHES", "1"]]}]