[{"is_off": ["STOVE", "1"]}, {"inside": [["FOOD_BUTTER", "1"], ["FRIDGE", "1"]]}, {"inside": [["FOOD_EGG", "1"], ["FRIDGE", "1"]]}, {"in": [["BOWL", "1"], ["KITCHEN CABINET", "1"]]}, {"location": [["TABLE", "1"], ["KITCHEN", "1"]]}, {"location": [["STOVE", "1"], ["KITCHEN", "1"]]}, {"location": [["PLATE", "1"], ["KITCHEN", "1"]]}, {"location": [["FOOD_SALT", "1"], ["KITCHEN", "1"]]}, {"location": [["FRIDGE", "1"], ["KITCHEN", "1"]]}, {"location": [["FORK", "1"], ["KITCHEN", "1"]]}, {"location": [["FRYINGPAN", "1"], ["KITCHEN", "1"]]}, {"location": [["BOWL", "1"], ["KITCHEN", "1"]]}, {"location": [["KITCHEN CABINET", "1"], ["KITCHEN", "1"]]}]