[{"is_off": ["faucet", "1"]}, {"atreach": [["clothes_pants", "1"], ["clothes_pants", "1"]]}, {"atreach": [["shower", "1"], ["clothes_pants", "1"]]}, {"atreach": [["faucet", "1"], ["clothes_pants", "1"]]}, {"atreach": [["soap", "1"], ["clothes_pants", "1"]]}, {"atreach": [["face", "1"], ["clothes_pants", "1"]]}, {"atreach": [["arms_both", "1"], ["clothes_pants", "1"]]}, {"atreach": [["feet_both", "1"], ["clothes_pants", "1"]]}, {"atreach": [["legs_both", "1"], ["clothes_pants", "1"]]}, {"in": [["clothes_pants", "1"], ["character", 1]]}, {"location": [["clothes_pants", "1"], ["bathroom", "1"]]}, {"location": [["shower", "1"], ["bathroom", "1"]]}, {"location": [["faucet", "1"], ["bathroom", "1"]]}, {"location": [["soap", "1"], ["bathroom", "1"]]}, {"location": [["face", "1"], ["bathroom", "1"]]}, {"location": [["arms_both", "1"], ["bathroom", "1"]]}, {"location": [["feet_both", "1"], ["bathroom", "1"]]}, {"location": [["legs_both", "1"], ["bathroom", "1"]]}]