[{"atreach": [["closet", "1"], ["closet", "1"]]}, {"atreach": [["clothes_shirt", "1"], ["closet", "1"]]}, {"atreach": [["clothes_skirt", "1"], ["closet", "1"]]}, {"atreach": [["shoes", "1"], ["closet", "1"]]}, {"atreach": [["floor", "1"], ["bed", "1"]]}, {"atreach": [["pajamas", "1"], ["bed", "1"]]}, {"atreach": [["basket_for_clothes", "1"], ["bed", "1"]]}, {"atreach": [["dresser", "1"], ["bed", "1"]]}, {"atreach": [["clothes_underwear", "1"], ["bed", "1"]]}, {"in": [["pajamas", "1"], ["character", 1]]}, {"location": [["closet", "1"], ["bedroom", "1"]]}, {"location": [["clothes_shirt", "1"], ["bedroom", "1"]]}, {"location": [["clothes_skirt", "1"], ["bedroom", "1"]]}, {"location": [["shoes", "1"], ["bedroom", "1"]]}, {"location": [["bed", "1"], ["bedroom", "1"]]}, {"location": [["floor", "1"], ["bedroom", "1"]]}, {"location": [["pajamas", "1"], ["bedroom", "1"]]}, {"location": [["basket_for_clothes", "1"], ["bedroom", "1"]]}, {"location": [["dresser", "1"], ["bedroom", "1"]]}, {"location": [["clothes_underwear", "1"], ["bedroom", "1"]]}, {"closed": ["closet", "1"]}, {"closed": ["dresser", "1"]}, {"inside": [["clothes_shirt", "1"], ["closet", "1"]]}, {"inside": [["clothes_skirt", "1"], ["closet", "1"]]}, {"inside": [["shoes", "1"], ["closet", "1"]]}, {"inside": [["clothes_underwear", "1"], ["dresser", "1"]]}, {"free": ["bed", "1"]}]